
{
  "specs": [
    {
      "title": "did x509 method specification",
      "spec_directory": "./spec",
      "output_path": "./docs",
      "markdown_paths": [
        "title.md", 
        "header.md",
        "toc.md",
        "foreword.md",
        "introduction.md",
        "scope.md",
        "example.md",
        "json_data_model.md",
        "identifier_syntax.md",
        "did_resolution_options.md",
        "operations.md",
        "security_privacy.md",
        "references.md"
      ],
      "logo": "https://raw.githubusercontent.com/trustoverip/logo-assets/master/logos/ToIP-Logo-Color-SolidDimensional-Horizontal-LightOnDark.svg",
      "logo_link": "https://github.com/trustoverip/tswg-did-x509-method-specification",
      "katex": true,
      "source": {
        "host": "github",
        "account": "trustoverip",
        "repo": "tswg-did-x509-method-specification"
      }
    }
  ]
}
